{
	"$schema": "http://schema.management.azure.com/schemas/2015-01-01/deploymentTemplate.json#",
	"contentVersion": "1.0.0.0",
	"parameters": {
		"factoryName": {
			"type": "string",
			"metadata": "Data Factory name",
			"defaultValue": "adf-project1-retentionanalysis"
		},
		"dLS_ADLS_Retention_Lake_accountKey": {
			"type": "secureString",
			"metadata": "Secure string for 'accountKey' of 'dLS_ADLS_Retention_Lake'"
		},
		"dimoLS_Databricks_Retention_accessToken": {
			"type": "secureString",
			"metadata": "Secure string for 'accessToken' of 'dimoLS_Databricks_Retention'"
		},
		"dLS_ADLS_Retention_Lake_properties_typeProperties_url": {
			"type": "string",
			"defaultValue": "https://retentionanalysis.dfs.core.windows.net/"
		},
		"dLS_KV_Retention_properties_typeProperties_baseUrl": {
			"type": "string",
			"defaultValue": "https://keyvault-liveproject1.vault.azure.net/"
		},
		"dLS_REST_WebinarPlatform_properties_typeProperties_url": {
			"type": "string",
			"defaultValue": "https://jsonplaceholder.typicode.com"
		},
		"dimoLS_Databricks_Retention_properties_typeProperties_existingClusterId": {
			"type": "string",
			"defaultValue": "0715-140757-jwp5y5cs"
		},
		"dLS_SQL_DocPlatform_properties_typeProperties_server": {
			"type": "string",
			"defaultValue": "sql-retentionanalysis.database.windows.net"
		},
		"dLS_SQL_DocPlatform_properties_typeProperties_database": {
			"type": "string",
			"defaultValue": "SQLdb-LiveProject1"
		},
		"dLS_SQL_DocPlatform_properties_typeProperties_userName": {
			"type": "string",
			"defaultValue": "Dimo"
		}
	},
	"variables": {
		"factoryId": "[concat('Microsoft.DataFactory/factories/', parameters('factoryName'))]"
	},
	"resources": [
		{
			"name": "[concat(parameters('factoryName'), '/dLS_ADLS_Retention_Lake')]",
			"type": "Microsoft.DataFactory/factories/linkedServices",
			"apiVersion": "2018-06-01",
			"properties": {
				"description": "This is Vaibhav's linked service for ADLS",
				"annotations": [],
				"type": "AzureBlobFS",
				"typeProperties": {
					"url": "[parameters('dLS_ADLS_Retention_Lake_properties_typeProperties_url')]",
					"accountKey": {
						"type": "SecureString",
						"value": "[parameters('dLS_ADLS_Retention_Lake_accountKey')]"
					}
				}
			},
			"dependsOn": []
		},
		{
			"name": "[concat(parameters('factoryName'), '/dLS_KV_Retention')]",
			"type": "Microsoft.DataFactory/factories/linkedServices",
			"apiVersion": "2018-06-01",
			"properties": {
				"description": "This is a Key Vault linked service made by Vaibhav. ",
				"annotations": [],
				"type": "AzureKeyVault",
				"typeProperties": {
					"baseUrl": "[parameters('dLS_KV_Retention_properties_typeProperties_baseUrl')]"
				}
			},
			"dependsOn": []
		},
		{
			"name": "[concat(parameters('factoryName'), '/dLS_REST_WebinarPlatform')]",
			"type": "Microsoft.DataFactory/factories/linkedServices",
			"apiVersion": "2018-06-01",
			"properties": {
				"description": "This linked service will connect with the REST APIs",
				"annotations": [],
				"type": "RestService",
				"typeProperties": {
					"url": "[parameters('dLS_REST_WebinarPlatform_properties_typeProperties_url')]",
					"enableServerCertificateValidation": true,
					"authenticationType": "Anonymous"
				}
			},
			"dependsOn": []
		},
		{
			"name": "[concat(parameters('factoryName'), '/dimoLS_Databricks_Retention')]",
			"type": "Microsoft.DataFactory/factories/linkedServices",
			"apiVersion": "2018-06-01",
			"properties": {
				"annotations": [],
				"type": "AzureDatabricks",
				"typeProperties": {
					"domain": "https://adb-7405606861759879.19.azuredatabricks.net",
					"accessToken": {
						"type": "SecureString",
						"value": "[parameters('dimoLS_Databricks_Retention_accessToken')]"
					},
					"existingClusterId": "[parameters('dimoLS_Databricks_Retention_properties_typeProperties_existingClusterId')]"
				}
			},
			"dependsOn": []
		},
		{
			"name": "[concat(parameters('factoryName'), '/dDS_Bronze_Document_Delta')]",
			"type": "Microsoft.DataFactory/factories/datasets",
			"apiVersion": "2018-06-01",
			"properties": {
				"linkedServiceName": {
					"referenceName": "dLS_ADLS_Retention_Lake",
					"type": "LinkedServiceReference"
				},
				"folder": {
					"name": "Project1- Retention Analysis"
				},
				"annotations": [],
				"type": "Parquet",
				"typeProperties": {
					"location": {
						"type": "AzureBlobFSLocation",
						"folderPath": "document",
						"fileSystem": "bronze"
					},
					"compressionCodec": "snappy"
				},
				"schema": []
			},
			"dependsOn": [
				"[concat(variables('factoryId'), '/linkedServices/dLS_ADLS_Retention_Lake')]"
			]
		},
		{
			"name": "[concat(parameters('factoryName'), '/dDS_Bronze_PeerInsights_Delta')]",
			"type": "Microsoft.DataFactory/factories/datasets",
			"apiVersion": "2018-06-01",
			"properties": {
				"linkedServiceName": {
					"referenceName": "dLS_ADLS_Retention_Lake",
					"type": "LinkedServiceReference"
				},
				"folder": {
					"name": "Project1- Retention Analysis"
				},
				"annotations": [],
				"type": "Parquet",
				"typeProperties": {
					"location": {
						"type": "AzureBlobFSLocation",
						"folderPath": "peerinsights",
						"fileSystem": "bronze"
					},
					"compressionCodec": "snappy"
				},
				"schema": []
			},
			"dependsOn": [
				"[concat(variables('factoryId'), '/linkedServices/dLS_ADLS_Retention_Lake')]"
			]
		},
		{
			"name": "[concat(parameters('factoryName'), '/dDS_Bronze_PeerInsights_JSON')]",
			"type": "Microsoft.DataFactory/factories/datasets",
			"apiVersion": "2018-06-01",
			"properties": {
				"linkedServiceName": {
					"referenceName": "dLS_ADLS_Retention_Lake",
					"type": "LinkedServiceReference"
				},
				"annotations": [],
				"type": "Json",
				"typeProperties": {
					"location": {
						"type": "AzureBlobFSLocation",
						"folderPath": "peerinsights",
						"fileSystem": "bronze"
					}
				},
				"schema": {}
			},
			"dependsOn": [
				"[concat(variables('factoryId'), '/linkedServices/dLS_ADLS_Retention_Lake')]"
			]
		},
		{
			"name": "[concat(parameters('factoryName'), '/dDS_Bronze_Webinar_Delta')]",
			"type": "Microsoft.DataFactory/factories/datasets",
			"apiVersion": "2018-06-01",
			"properties": {
				"linkedServiceName": {
					"referenceName": "dLS_ADLS_Retention_Lake",
					"type": "LinkedServiceReference"
				},
				"folder": {
					"name": "Project1- Retention Analysis"
				},
				"annotations": [],
				"type": "Parquet",
				"typeProperties": {
					"location": {
						"type": "AzureBlobFSLocation",
						"folderPath": "webinar",
						"fileSystem": "bronze"
					},
					"compressionCodec": "snappy"
				},
				"schema": []
			},
			"dependsOn": [
				"[concat(variables('factoryId'), '/linkedServices/dLS_ADLS_Retention_Lake')]"
			]
		},
		{
			"name": "[concat(parameters('factoryName'), '/dDS_Bronze_Webinar_JSON')]",
			"type": "Microsoft.DataFactory/factories/datasets",
			"apiVersion": "2018-06-01",
			"properties": {
				"linkedServiceName": {
					"referenceName": "dLS_ADLS_Retention_Lake",
					"type": "LinkedServiceReference"
				},
				"annotations": [],
				"type": "Json",
				"typeProperties": {
					"location": {
						"type": "AzureBlobFSLocation",
						"folderPath": "webinar",
						"fileSystem": "bronze"
					}
				},
				"schema": {}
			},
			"dependsOn": [
				"[concat(variables('factoryId'), '/linkedServices/dLS_ADLS_Retention_Lake')]"
			]
		},
		{
			"name": "[concat(parameters('factoryName'), '/dDS_Landing_PeerInsights_JSON')]",
			"type": "Microsoft.DataFactory/factories/datasets",
			"apiVersion": "2018-06-01",
			"properties": {
				"linkedServiceName": {
					"referenceName": "dLS_ADLS_Retention_Lake",
					"type": "LinkedServiceReference"
				},
				"folder": {
					"name": "Project1- Retention Analysis"
				},
				"annotations": [],
				"type": "Json",
				"typeProperties": {
					"location": {
						"type": "AzureBlobFSLocation",
						"fileName": "peer_insights_raw.json",
						"folderPath": "peer_insights/2026/7",
						"fileSystem": "landing"
					}
				},
				"schema": {
					"type": "object",
					"properties": {
						"source": {
							"type": "string"
						},
						"extract_date": {
							"type": "string"
						},
						"total_reviews": {
							"type": "integer"
						},
						"reviews": {
							"type": "array",
							"items": {
								"type": "object",
								"properties": {
									"review_id": {
										"type": "string"
									},
									"user_email": {
										"type": "string"
									},
									"product_reviewed": {
										"type": "string"
									},
									"rating": {
										"type": "integer"
									},
									"review_text": {
										"type": "string"
									},
									"review_date": {
										"type": "string"
									},
									"view_count": {
										"type": "integer"
									},
									"helpful_count": {
										"type": "integer"
									},
									"product_category": {
										"type": "string"
									}
								}
							}
						}
					}
				}
			},
			"dependsOn": [
				"[concat(variables('factoryId'), '/linkedServices/dLS_ADLS_Retention_Lake')]"
			]
		},
		{
			"name": "[concat(parameters('factoryName'), '/dDS_Landing_Webinar_JSON')]",
			"type": "Microsoft.DataFactory/factories/datasets",
			"apiVersion": "2018-06-01",
			"properties": {
				"linkedServiceName": {
					"referenceName": "dLS_ADLS_Retention_Lake",
					"type": "LinkedServiceReference"
				},
				"folder": {
					"name": "Project1- Retention Analysis"
				},
				"annotations": [],
				"type": "Json",
				"typeProperties": {
					"location": {
						"type": "AzureBlobFSLocation",
						"fileName": "webinar_events_raw.json",
						"folderPath": "webinar/2026/7",
						"fileSystem": "landing"
					}
				},
				"schema": {
					"type": "object",
					"properties": {
						"source": {
							"type": "string"
						},
						"extract_date": {
							"type": "string"
						},
						"total_events": {
							"type": "integer"
						},
						"events": {
							"type": "array",
							"items": {
								"type": "object",
								"properties": {
									"event_id": {
										"type": "string"
									},
									"webinar_id": {
										"type": "string"
									},
									"webinar_title": {
										"type": "string"
									},
									"user_id": {
										"type": "integer"
									},
									"event_type": {
										"type": "string"
									},
									"event_timestamp": {
										"type": "string"
									},
									"duration_minutes": {
										"type": "integer"
									},
									"webinar_date": {
										"type": "string"
									},
									"attendee_email": {
										"type": "string"
									}
								}
							}
						}
					}
				}
			},
			"dependsOn": [
				"[concat(variables('factoryId'), '/linkedServices/dLS_ADLS_Retention_Lake')]"
			]
		},
		{
			"name": "[concat(parameters('factoryName'), '/dLS_SQL_DocPlatform')]",
			"type": "Microsoft.DataFactory/factories/linkedServices",
			"apiVersion": "2018-06-01",
			"properties": {
				"description": "This is a linked service for database created by Vaibhav",
				"annotations": [],
				"type": "AzureSqlDatabase",
				"typeProperties": {
					"server": "[parameters('dLS_SQL_DocPlatform_properties_typeProperties_server')]",
					"database": "[parameters('dLS_SQL_DocPlatform_properties_typeProperties_database')]",
					"encrypt": "mandatory",
					"trustServerCertificate": true,
					"authenticationType": "SQL",
					"userName": "[parameters('dLS_SQL_DocPlatform_properties_typeProperties_userName')]",
					"password": {
						"type": "AzureKeyVaultSecret",
						"store": {
							"referenceName": "dLS_KV_Retention",
							"type": "LinkedServiceReference"
						},
						"secretName": "sql-project1-password"
					},
					"alwaysEncryptedSettings": {
						"alwaysEncryptedAkvAuthType": "ManagedIdentity"
					}
				}
			},
			"dependsOn": [
				"[concat(variables('factoryId'), '/linkedServices/dLS_KV_Retention')]"
			]
		},
		{
			"name": "[concat(parameters('factoryName'), '/d_PL_Bronze_PeerInsights_Ingest')]",
			"type": "Microsoft.DataFactory/factories/pipelines",
			"apiVersion": "2018-06-01",
			"properties": {
				"description": "Purpose: landing/peer_insights/ se JSON file uthao → bronze/peer_insights/ mein Parquet mein copy karo",
				"activities": [
					{
						"name": "DimoCopy_PeerInsights_To_Bronze",
						"type": "Copy",
						"dependsOn": [],
						"policy": {
							"timeout": "0.12:00:00",
							"retry": 0,
							"retryIntervalInSeconds": 30,
							"secureOutput": false,
							"secureInput": false
						},
						"userProperties": [],
						"typeProperties": {
							"source": {
								"type": "JsonSource",
								"storeSettings": {
									"type": "AzureBlobFSReadSettings",
									"recursive": true,
									"enablePartitionDiscovery": false
								},
								"formatSettings": {
									"type": "JsonReadSettings"
								}
							},
							"sink": {
								"type": "JsonSink",
								"storeSettings": {
									"type": "AzureBlobFSWriteSettings"
								},
								"formatSettings": {
									"type": "JsonWriteSettings"
								}
							},
							"enableStaging": false,
							"enableSkipIncompatibleRow": true
						},
						"inputs": [
							{
								"referenceName": "dDS_Landing_PeerInsights_JSON",
								"type": "DatasetReference",
								"parameters": {}
							}
						],
						"outputs": [
							{
								"referenceName": "dDS_Bronze_PeerInsights_JSON",
								"type": "DatasetReference",
								"parameters": {}
							}
						]
					}
				],
				"policy": {
					"elapsedTimeMetric": {}
				},
				"folder": {
					"name": "Child Pipelines"
				},
				"annotations": []
			},
			"dependsOn": [
				"[concat(variables('factoryId'), '/datasets/dDS_Landing_PeerInsights_JSON')]",
				"[concat(variables('factoryId'), '/datasets/dDS_Bronze_PeerInsights_JSON')]"
			]
		},
		{
			"name": "[concat(parameters('factoryName'), '/d_PL_Bronze_Webinar_Ingest')]",
			"type": "Microsoft.DataFactory/factories/pipelines",
			"apiVersion": "2018-06-01",
			"properties": {
				"activities": [
					{
						"name": "dimo_Copy_WebinarEvents_To_Bronze",
						"type": "Copy",
						"dependsOn": [],
						"policy": {
							"timeout": "0.12:00:00",
							"retry": 0,
							"retryIntervalInSeconds": 30,
							"secureOutput": false,
							"secureInput": false
						},
						"userProperties": [],
						"typeProperties": {
							"source": {
								"type": "JsonSource",
								"storeSettings": {
									"type": "AzureBlobFSReadSettings",
									"recursive": true,
									"enablePartitionDiscovery": false
								},
								"formatSettings": {
									"type": "JsonReadSettings"
								}
							},
							"sink": {
								"type": "JsonSink",
								"storeSettings": {
									"type": "AzureBlobFSWriteSettings"
								},
								"formatSettings": {
									"type": "JsonWriteSettings"
								}
							},
							"enableStaging": false,
							"enableSkipIncompatibleRow": true
						},
						"inputs": [
							{
								"referenceName": "dDS_Landing_Webinar_JSON",
								"type": "DatasetReference",
								"parameters": {}
							}
						],
						"outputs": [
							{
								"referenceName": "dDS_Bronze_Webinar_JSON",
								"type": "DatasetReference",
								"parameters": {}
							}
						]
					}
				],
				"policy": {
					"elapsedTimeMetric": {}
				},
				"folder": {
					"name": "Child Pipelines"
				},
				"annotations": []
			},
			"dependsOn": [
				"[concat(variables('factoryId'), '/datasets/dDS_Landing_Webinar_JSON')]",
				"[concat(variables('factoryId'), '/datasets/dDS_Bronze_Webinar_JSON')]"
			]
		},
		{
			"name": "[concat(parameters('factoryName'), '/dDS_SQL_DocumentDownloads')]",
			"type": "Microsoft.DataFactory/factories/datasets",
			"apiVersion": "2018-06-01",
			"properties": {
				"linkedServiceName": {
					"referenceName": "dLS_SQL_DocPlatform",
					"type": "LinkedServiceReference"
				},
				"folder": {
					"name": "Project1- Retention Analysis"
				},
				"annotations": [],
				"type": "AzureSqlTable",
				"schema": [
					{
						"name": "download_id",
						"type": "int",
						"precision": 10
					},
					{
						"name": "doc_id",
						"type": "varchar"
					},
					{
						"name": "doc_title",
						"type": "varchar"
					},
					{
						"name": "doc_category",
						"type": "varchar"
					},
					{
						"name": "user_email",
						"type": "varchar"
					},
					{
						"name": "download_timestamp",
						"type": "datetime",
						"precision": 23,
						"scale": 3
					},
					{
						"name": "file_size_kb",
						"type": "int",
						"precision": 10
					},
					{
						"name": "platform",
						"type": "varchar"
					},
					{
						"name": "is_premium_content",
						"type": "bit"
					},
					{
						"name": "created_at",
						"type": "datetime",
						"precision": 23,
						"scale": 3
					}
				],
				"typeProperties": {
					"schema": "dbo",
					"table": "document_downloads"
				}
			},
			"dependsOn": [
				"[concat(variables('factoryId'), '/linkedServices/dLS_SQL_DocPlatform')]"
			]
		},
		{
			"name": "[concat(parameters('factoryName'), '/d_PL_Bronze_Document_Ingest')]",
			"type": "Microsoft.DataFactory/factories/pipelines",
			"apiVersion": "2018-06-01",
			"properties": {
				"activities": [
					{
						"name": "Copy_DocumentDownloads_To_Bronze",
						"type": "Copy",
						"dependsOn": [],
						"policy": {
							"timeout": "0.12:00:00",
							"retry": 0,
							"retryIntervalInSeconds": 30,
							"secureOutput": false,
							"secureInput": false
						},
						"userProperties": [],
						"typeProperties": {
							"source": {
								"type": "AzureSqlSource",
								"queryTimeout": "02:00:00",
								"isolationLevel": "ReadCommitted",
								"partitionOption": "None"
							},
							"sink": {
								"type": "ParquetSink",
								"storeSettings": {
									"type": "AzureBlobFSWriteSettings"
								},
								"formatSettings": {
									"type": "ParquetWriteSettings"
								}
							},
							"enableStaging": false,
							"enableSkipIncompatibleRow": true,
							"translator": {
								"type": "TabularTranslator",
								"typeConversion": true,
								"typeConversionSettings": {
									"allowDataTruncation": true,
									"treatBooleanAsNumber": false
								}
							}
						},
						"inputs": [
							{
								"referenceName": "dDS_SQL_DocumentDownloads",
								"type": "DatasetReference",
								"parameters": {}
							}
						],
						"outputs": [
							{
								"referenceName": "dDS_Bronze_Document_Delta",
								"type": "DatasetReference",
								"parameters": {}
							}
						]
					}
				],
				"policy": {
					"elapsedTimeMetric": {}
				},
				"folder": {
					"name": "Child Pipelines"
				},
				"annotations": []
			},
			"dependsOn": [
				"[concat(variables('factoryId'), '/datasets/dDS_SQL_DocumentDownloads')]",
				"[concat(variables('factoryId'), '/datasets/dDS_Bronze_Document_Delta')]"
			]
		},
		{
			"name": "[concat(parameters('factoryName'), '/d_PL_Master_Orchestrator')]",
			"type": "Microsoft.DataFactory/factories/pipelines",
			"apiVersion": "2018-06-01",
			"properties": {
				"activities": [
					{
						"name": "Dimo_Exec_Pipeline_Webinar",
						"type": "ExecutePipeline",
						"dependsOn": [],
						"policy": {
							"secureInput": false
						},
						"userProperties": [],
						"typeProperties": {
							"pipeline": {
								"referenceName": "d_PL_Bronze_Webinar_Ingest",
								"type": "PipelineReference"
							},
							"waitOnCompletion": true,
							"parameters": {}
						}
					},
					{
						"name": "Dimo_Exec_Pipeline_Document",
						"type": "ExecutePipeline",
						"dependsOn": [],
						"policy": {
							"secureInput": false
						},
						"userProperties": [],
						"typeProperties": {
							"pipeline": {
								"referenceName": "d_PL_Bronze_Document_Ingest",
								"type": "PipelineReference"
							},
							"waitOnCompletion": true,
							"parameters": {}
						}
					},
					{
						"name": "Dimo_Exec_Pipeline_PeerInsights",
						"type": "ExecutePipeline",
						"dependsOn": [],
						"policy": {
							"secureInput": false
						},
						"userProperties": [],
						"typeProperties": {
							"pipeline": {
								"referenceName": "d_PL_Bronze_PeerInsights_Ingest",
								"type": "PipelineReference"
							},
							"waitOnCompletion": true,
							"parameters": {}
						}
					},
					{
						"name": "Dimo_Exec_Notebook_Silver_Standardize",
						"type": "DatabricksNotebook",
						"dependsOn": [
							{
								"activity": "Dimo_Exec_Pipeline_Webinar",
								"dependencyConditions": [
									"Succeeded"
								]
							},
							{
								"activity": "Dimo_Exec_Pipeline_Document",
								"dependencyConditions": [
									"Succeeded"
								]
							},
							{
								"activity": "Dimo_Exec_Pipeline_PeerInsights",
								"dependencyConditions": [
									"Succeeded"
								]
							}
						],
						"policy": {
							"timeout": "0.12:00:00",
							"retry": 0,
							"retryIntervalInSeconds": 30,
							"secureOutput": false,
							"secureInput": false
						},
						"userProperties": [],
						"typeProperties": {
							"notebookPath": "/Users/vaibhav.dimri23@gmail.com/Dimo_Retention_Analysis/Silver/01_silver_standardize"
						},
						"linkedServiceName": {
							"referenceName": "dimoLS_Databricks_Retention",
							"type": "LinkedServiceReference"
						}
					},
					{
						"name": "Dimo_Act_on_Any_Failure",
						"type": "WebActivity",
						"dependsOn": [
							{
								"activity": "Dimo_Exec_Pipeline_Document",
								"dependencyConditions": [
									"Failed"
								]
							},
							{
								"activity": "Dimo_Exec_Pipeline_Webinar",
								"dependencyConditions": [
									"Failed"
								]
							},
							{
								"activity": "Dimo_Exec_Pipeline_PeerInsights",
								"dependencyConditions": [
									"Failed"
								]
							}
						],
						"policy": {
							"timeout": "0.12:00:00",
							"retry": 0,
							"retryIntervalInSeconds": 30,
							"secureOutput": false,
							"secureInput": false
						},
						"userProperties": [],
						"typeProperties": {
							"method": "POST",
							"headers": {},
							"url": "https://webhook.site/47accdc2-a0b5-4acc-ba17-d2a005db6a87",
							"body": {
								"status": "failure",
								"pipeline": "@{pipeline().PipelineName}",
								"message": "Pipeline failed - check ADF Monitor"
							}
						}
					}
				],
				"policy": {
					"elapsedTimeMetric": {}
				},
				"folder": {
					"name": "Parent Pipeline"
				},
				"annotations": []
			},
			"dependsOn": [
				"[concat(variables('factoryId'), '/pipelines/d_PL_Bronze_Webinar_Ingest')]",
				"[concat(variables('factoryId'), '/pipelines/d_PL_Bronze_Document_Ingest')]",
				"[concat(variables('factoryId'), '/pipelines/d_PL_Bronze_PeerInsights_Ingest')]",
				"[concat(variables('factoryId'), '/linkedServices/dimoLS_Databricks_Retention')]"
			]
		},
		{
			"name": "[concat(parameters('factoryName'), '/Dimo_TRG_Monthly_1st_9AM')]",
			"type": "Microsoft.DataFactory/factories/triggers",
			"apiVersion": "2018-06-01",
			"properties": {
				"annotations": [],
				"runtimeState": "Stopped",
				"pipelines": [
					{
						"pipelineReference": {
							"referenceName": "d_PL_Master_Orchestrator",
							"type": "PipelineReference"
						},
						"parameters": {}
					}
				],
				"type": "ScheduleTrigger",
				"typeProperties": {
					"recurrence": {
						"frequency": "Month",
						"interval": 1,
						"startTime": "2026-07-17T19:17:00",
						"timeZone": "India Standard Time"
					}
				}
			},
			"dependsOn": [
				"[concat(variables('factoryId'), '/pipelines/d_PL_Master_Orchestrator')]"
			]
		}
	]
}